datasnatch/BLAST.py
datasnatch/CDD.py
datasnatch/__init__.py
datasnatch-0.0.1.dist-info/LICENSE
datasnatch-0.0.1.dist-info/METADATA
datasnatch-0.0.1.dist-info/WHEEL
datasnatch-0.0.1.dist-info/RECORD
