Metadata-Version: 2.1
Name: datasnatch
Version: 0.0.1
Summary: Convenience methods for data analysis.
License: MIT
Author: kosmolebryce
Author-email: k.lebryce@pm.me
Requires-Python: >=3.9.0,<4.0.0
Classifier: License :: OSI Approved :: MIT License
Classifier: Programming Language :: Python :: 3
Classifier: Programming Language :: Python :: 3.9
Classifier: Programming Language :: Python :: 3.10
Classifier: Programming Language :: Python :: 3.11
Classifier: Programming Language :: Python :: 3.12
Classifier: Programming Language :: Python :: 3.13
Requires-Dist: biopython (>=1.80.0,<2.0.0)
Requires-Dist: matplotlib (>=3.9.0,<4.0.0)
Requires-Dist: pandas (>=2.0.0,<3.0.0)
Requires-Dist: python-dotenv (>=1.0.0,<2.0.0)
Requires-Dist: seaborn (>=0.13.0,<0.14.0)
